Lesson2/rtl/event_counter.sv
module event_counter (
    input            event_triggered,  //! Event occurred, increment the count
    input            rst,              //! Reset the count to zero
    input            hold,             //! Hold the current count even if an event is triggered
    output reg [7:0] count = 0         //! Count the number of events that have occurred
);

  always @(posedge event_triggered, posedge rst) begin
    if (rst) count <= 0;
    else if (!hold) count <= count + 1;
  end

endmodule

Lesson2/tb/event_counter_tb.sv
`timescale 1ns / 1ps

module event_counter_tb;

  // Parameters

  // Ports
  reg event_triggered = 0;
  reg rst = 0;
  reg hold = 0;
  wire [7:0] count;

  event_counter event_counter_dut (
      .event_triggered(event_triggered),
      .rst(rst),
      .hold(hold),
      .count(count)
  );

  initial begin
    begin
      $dumpfile("event_counter_tb.vcd");
      $dumpvars;
      test(5);
      $finish;
    end
  end

  task automatic test;
    input integer nTest;
    begin
      #(100);
      hold = 0;
      repeat (nTest) random_event;
      hold = 1;
      repeat (nTest) random_event;
      rst = 1;
      #(10);
      rst = 0;
      #(100);
    end
  endtask  //automatic

  task automatic random_event;
    begin
      #($urandom % 100 + 1);
      event_triggered = 1;
      #($urandom % 10 + 1);
      event_triggered = 0;
    end
  endtask  //automatic

endmodule

Lesson2/event_counter_tb.vcd
$date
	Fri Oct 25 01:05:56 2024
$end
$version
	Icarus Verilog
$end
$timescale
	1ps
$end
$scope module event_counter_tb $end
$var wire 8 ! count [7:0] $end
$var reg 1 " event_triggered $end
$var reg 1 # hold $end
$var reg 1 $ rst $end
$scope module event_counter_dut $end
$var wire 1 " event_triggered $end
$var wire 1 # hold $end
$var wire 1 $ rst $end
$var reg 8 % count [7:0] $end
$upscope $end
$scope task random_event $end
$upscope $end
$scope task test $end
$upscope $end
$upscope $end
$enddefinitions $end
$comment Show the parameter values. $end
$dumpall
$end
#0
$dumpvars
b0 %
0$
0#
0"
b0 !
$end
#197000
b1 !
b1 %
1"
#207000
0"
#217000
b10 !
b10 %
1"
#227000
0"
#233000
b11 !
b11 %
1"
#239000
0"
#317000
b100 !
b100 %
1"
#322000
0"
#332000
b101 !
b101 %
1"
#340000
1#
0"
#407000
1"
#413000
0"
#491000
1"
#492000
0"
#530000
1"
#539000
0"
#589000
1"
#594000
0"
#628000
1"
#636000
b0 !
b0 %
1$
0"
#646000
0$
