Lesson2/rtl/shift_reg.sv
module shift_reg #(
    parameter DEPTH = 4  //! Depth of the shift register
) (
    input                  clk,  //! Clock signal to trigger data shift on rising edge
    input                  rst,  //! Reset signal to initialize the register to 0
    input                  en,   //! Enable signal to allow shifting when high
    input                  d,    //! Data input for the shift register
    output reg [DEPTH-1:0] q     //! Output of the shift register holding the shifted data
);

  always @(posedge clk, posedge rst) begin
    if (rst) q <= 0;  // Reset the register to 0 when rst is high
    else if (en) q <= {d, q[DEPTH-1:1]};  // Shift data in when enable is high
  end

endmodule

Lesson2/tb/shift_reg_tb.sv
module shift_reg_tb;

  // Parameters
  localparam CLK_PERIOD = 10;
  localparam DEPTH = 4;

  // Ports
  reg clk = 0;
  reg rst = 0;
  reg en = 0;
  reg d = 0;
  wire [DEPTH-1:0] q;

  shift_reg #(
      .DEPTH(DEPTH)
  ) shift_reg_dut (
      .clk(clk),
      .rst(rst),
      .en (en),
      .d  (d),
      .q  (q)
  );

  initial begin
    begin
      $dumpfile("shift_reg_tb.vcd");
      $dumpvars;
      reset(1);
      nopclk(2);
      test($urandom, 10);
      nopclk(2);
      $finish;
    end
  end

  task automatic test;
    input integer seq;
    input integer n;
    integer seq_idx;
    begin
      seq_idx = 0;
      en = 1;
      repeat (n) begin
        d = seq[seq_idx];
        @(negedge clk);
        seq_idx = seq_idx + 1;
      end
      en = 0;
    end
  endtask  //automatic

  task automatic nopclk;
    input integer n;
    begin
      repeat (n) @(negedge clk);
    end
  endtask  //automatic

  task automatic reset;
    input integer n;
    begin
      rst = 1;
      repeat (n) @(negedge clk);
      rst = 0;
    end
  endtask  //automatic

  always #(CLK_PERIOD / 2) clk <= !clk;

endmodule

Lesson2/shift_reg_tb.vcd
$date
	Mon Oct 28 10:46:17 2024
$end
$version
	Icarus Verilog
$end
$timescale
	1s
$end
$scope module shift_reg_tb $end
$var wire 4 ! q [3:0] $end
$var parameter 32 " CLK_PERIOD $end
$var parameter 32 # DEPTH $end
$var reg 1 $ clk $end
$var reg 1 % d $end
$var reg 1 & en $end
$var reg 1 ' rst $end
$scope module shift_reg_dut $end
$var wire 1 $ clk $end
$var wire 1 % d $end
$var wire 1 & en $end
$var wire 1 ' rst $end
$var parameter 32 ( DEPTH $end
$var reg 4 ) q [3:0] $end
$upscope $end
$scope task nopclk $end
$upscope $end
$scope task reset $end
$upscope $end
$scope task test $end
$upscope $end
$upscope $end
$enddefinitions $end
$comment Show the parameter values. $end
$dumpall
b100 (
b100 #
b1010 "
$end
#0
$dumpvars
b0 )
1'
0&
0%
0$
b0 !
$end
#5
1$
#10
0'
0$
#15
1$
#20
0$
#25
1$
#30
1&
0$
#35
1$
#40
0$
#45
1$
#50
1%
0$
#55
b1000 !
b1000 )
1$
#60
0%
0$
#65
b100 !
b100 )
1$
#70
0$
#75
b10 !
b10 )
1$
#80
1%
0$
#85
b1001 !
b1001 )
1$
#90
0%
0$
#95
b100 !
b100 )
1$
#100
0$
#105
b10 !
b10 )
1$
#110
1%
0$
#115
b1001 !
b1001 )
1$
#120
0%
0$
#125
b100 !
b100 )
1$
#130
0&
0$
