Lesson2/rtl/up_dw_cnt.sv
module up_dw_cnt #(
    parameter CNT_WIDTH = 4  //! Bit width of the counter
) (
    input                      clk,    //! Clock signal
    input                      rst,    //! Reset the counter
    input                      en,     //! enable counter
    input                      up_dw,  //! Up/Down (1 for Up, 0 for Down)
    output reg [CNT_WIDTH-1:0] cnt     //! Current count value
);

  always @(posedge clk, posedge rst) begin
    if (rst) cnt <= 0;
    else if (en) cnt <= up_dw ? cnt + 1 : cnt - 1;
  end

endmodule

Lesson2/tb/up_dw_cnt_tb.sv
`timescale 1ns / 1ps

module up_dw_cnt_tb;

  // Parameters
  localparam CLK_PERIOD = 10;
  localparam CNT_WIDTH = 4;

  // Ports
  reg                  clk = 0;
  reg                  rst = 0;
  reg                  en = 0;
  reg                  up_dw = 0;
  wire [CNT_WIDTH-1:0] cnt;

  up_dw_cnt #(
      .CNT_WIDTH(CNT_WIDTH)
  ) up_dw_cnt_dut (
      .clk  (clk),
      .rst  (rst),
      .en   (en),
      .up_dw(up_dw),
      .cnt  (cnt)
  );

  initial begin
    begin
      $dumpfile("up_dw_cnt_tb.vcd");
      $dumpvars;
      reset(1);
      nopclk(2);
      up_dw_test(1, 5);
      up_dw_test(0, 3);
      nopclk(2);
      $finish;
    end
  end

  task automatic nopclk;
    input integer n;
    begin
      repeat (n) @(negedge clk);
    end
  endtask  //automatic

  task automatic reset;
    input integer n;
    begin
      rst = 1;
      repeat (n) @(negedge clk);
      rst = 0;
    end
  endtask  //automatic

  task automatic up_dw_test;
    input i_up_dw;
    input integer n;
    begin
      en = 1;
      up_dw = i_up_dw;
      repeat (n) @(negedge clk);
      en = 0;
    end
  endtask  //automatic

  always #(CLK_PERIOD / 2) clk <= !clk;

endmodule

Lesson2/up_dw_cnt_tb.vcd
$date
	Mon Oct 28 10:11:15 2024
$end
$version
	Icarus Verilog
$end
$timescale
	1ps
$end
$scope module up_dw_cnt_tb $end
$var wire 4 ! cnt [3:0] $end
$var parameter 32 " CLK_PERIOD $end
$var parameter 32 # CNT_WIDTH $end
$var reg 1 $ clk $end
$var reg 1 % en $end
$var reg 1 & rst $end
$var reg 1 ' up_dw $end
$scope module up_dw_cnt_dut $end
$var wire 1 $ clk $end
$var wire 1 % en $end
$var wire 1 & rst $end
$var wire 1 ' up_dw $end
$var parameter 32 ( CNT_WIDTH $end
$var reg 4 ) cnt [3:0] $end
$upscope $end
$scope task nopclk $end
$upscope $end
$scope task reset $end
$upscope $end
$scope task up_dw_test $end
$upscope $end
$upscope $end
$enddefinitions $end
$comment Show the parameter values. $end
$dumpall
b100 (
b100 #
b1010 "
$end
#0
$dumpvars
b0 )
0'
1&
0%
0$
b0 !
$end
#5000
1$
#10000
0&
0$
#15000
1$
#20000
0$
#25000
1$
#30000
1'
1%
0$
#35000
b1 !
b1 )
1$
#40000
0$
#45000
b10 !
b10 )
1$
#50000
0$
#55000
b11 !
b11 )
1$
#60000
0$
#65000
b100 !
b100 )
1$
#70000
0$
#75000
b101 !
b101 )
1$
#80000
0'
1%
0$
#85000
b100 !
b100 )
1$
#90000
0$
#95000
b11 !
b11 )
1$
#100000
0$
#105000
b10 !
b10 )
1$
#110000
0%
0$
